<?xml version="1.0" encoding="UTF-8" standalone="yes"?>
<RegularExpressionProtection name="REP-ValidateRequestExpresion">
    <DisplayName>REP-ValidateRequestExpresion</DisplayName>
    <Source>request</Source>
    <JSONPayload escapeSlashCharacter="true">
        <JSONPath>
            <Expression>$.</Expression>
            <Pattern>&lt;\s*script\b[^&gt;]*&gt;[^&lt;]+&lt;\s*\/\s*script\s*&gt;
          </Pattern>
            <Pattern>n\s*\\\\\s*slash</Pattern>
            <Pattern>n\s*\/\s*slash</Pattern>
            <Pattern>n\s*\\"\s*quotes</Pattern>
            <Pattern>n\s*\\b\s*space</Pattern>
            <Pattern>n\s*\\f\s*forwardfeed</Pattern>
            <Pattern>n\s*\\n\s*newline</Pattern>
            <Pattern>n\s*\\r\s*carria</Pattern>
            <Pattern>n\s*\\t\s*tab</Pattern>
            <Pattern>n\s*\\uFFFF\s*hex</Pattern>
            <Pattern>[\s]*(?i)((delete)|(exec)|(drop\s*table)|(insert)|(shutdown)|(update)|(\bor\b))</Pattern>
        </JSONPath>
    </JSONPayload>
</RegularExpressionProtection>